britishcycling_clubs/__init__.py
britishcycling_clubs/manager.py
britishcycling_clubs/profile.py
britishcycling_clubs/py.typed
CHANGELOG.md
britishcycling_clubs-0.11.0.dist-info/LICENSE
britishcycling_clubs-0.11.0.dist-info/METADATA
britishcycling_clubs-0.11.0.dist-info/WHEEL
britishcycling_clubs-0.11.0.dist-info/RECORD
