Metadata-Version: 2.1
Name: britishcycling-clubs
Version: 0.11.0
Summary: Unofficial library to automate aspects of British/Scottish/Welsh Cycling's club Membership Manager system
Home-page: https://github.com/elliot-100/britishcycling-clubs
License: GPL-3.0-only
Author: elliot-100
Author-email: 3186037+elliot-100@users.noreply.github.com
Requires-Python: >=3.8
Classifier: License :: OSI Approved :: GNU General Public License v3 (GPLv3)
Classifier: Programming Language :: Python :: 3
Classifier: Programming Language :: Python :: 3.8
Classifier: Programming Language :: Python :: 3.9
Classifier: Programming Language :: Python :: 3.10
Classifier: Programming Language :: Python :: 3.11
Classifier: Programming Language :: Python :: 3.12
Classifier: Programming Language :: Python :: 3.13
Requires-Dist: beautifulsoup4 (>=4.12.2)
Requires-Dist: playwright (>=1.39.0)
Requires-Dist: requests (>=2.23.1)
Project-URL: Repository, https://github.com/elliot-100/britishcycling-clubs
